{
  "timestamp": "2026-04-05T22:35:55.198794",
  "current_features": {
    "combat": [
      "MicroCombat",
      "CombatManager",
      "AdvancedMicroControllerV3"
    ],
    "economy": [
      "EconomyManager",
      "ProductionController"
    ],
    "defense": [
      "DefenseCoordinator",
      "MultiBaseDefense"
    ],
    "strategy": [
      "StrategyManager",
      "StrategyManagerV2"
    ],
    "scouting": [
      "EarlyScoutSystem",
      "IntelManager"
    ],
    "production": [
      "UnitFactory",
      "ProductionController"
    ],
    "upgrades": [
      "UpgradeManager",
      "EvolutionUpgradeManager"
    ],
    "creep": [
      "CreepManager",
      "CreepAutomationV2"
    ]
  },
  "missing_features": [
    {
      "category": "AI/ML",
      "feature": "Neural Network Prediction",
      "description": "Predict enemy moves using neural networks",
      "priority": "HIGH"
    },
    {
      "category": "Combat",
      "feature": "Formation AI",
      "description": "Advanced formation control for armies",
      "priority": "MEDIUM"
    },
    {
      "category": "Strategy",
      "feature": "Meta Game Analyzer",
      "description": "Analyze current meta and adapt strategy",
      "priority": "HIGH"
    },
    {
      "category": "Economy",
      "feature": "Resource Prediction",
      "description": "Predict resource needs for future builds",
      "priority": "MEDIUM"
    },
    {
      "category": "Defense",
      "feature": "Proxy Detection",
      "description": "Detect and counter proxy strategies",
      "priority": "HIGH"
    },
    {
      "category": "Scouting",
      "feature": "Enemy Composition Analysis",
      "description": "Analyze enemy army composition",
      "priority": "MEDIUM"
    },
    {
      "category": "Production",
      "feature": "Adaptive Production",
      "description": "Adapt production based on game state",
      "priority": "MEDIUM"
    },
    {
      "category": "Multiplayer",
      "feature": "Team Comms",
      "description": "Team communication for 2v2",
      "priority": "LOW"
    }
  ]
}